mediapills/__init__.py
mediapills/core/__init__.py
mediapills/core/controllers.py
mediapills/core/loggers.py
mediapills/core/repositories.py
mediapills/core/requests.py
mediapills/core/responses.py
mediapills/core/domain/__init__.py
mediapills/core/domain/entities.py
mediapills/core/domain/exceptions.py
mediapills/core/domain/loggers.py
mediapills/core/domain/outputs.py
mediapills/core/domain/repositories.py
mediapills/core/domain/usecases.py
mediapills.core-0.0.2.dist-info/LICENSE.md
mediapills.core-0.0.2.dist-info/METADATA
mediapills.core-0.0.2.dist-info/WHEEL
mediapills.core-0.0.2.dist-info/top_level.txt
mediapills.core-0.0.2.dist-info/zip-safe
mediapills.core-0.0.2.dist-info/RECORD
