Metadata-Version: 2.1
Name: mediapills.core
Version: 0.0.2
Summary: A small Python framework domain micro kernel
Home-page: https://github.com/mediapills/core.git
Author: Andriy Yatskovets
Author-email: andriy.yatskovets@gmail.com
License: 'MIT'
Project-URL: Bug Tracker, https://github.com/mediapills/core/issues
Project-URL: Source Code, https://github.com/mediapills/core
Keywords: 'Patterns','Kernel','Use-Case','Entity','Controller'
Platform: 'any'
Classifier: Development Status :: 1 - Planning
Classifier: Intended Audience :: Developers
Classifier: Intended Audience :: Education
Classifier: License :: OSI Approved :: MIT License
Classifier: Programming Language :: Python
Classifier: Programming Language :: Python :: 3 :: Only
Classifier: Programming Language :: Python :: 3.6
Classifier: Programming Language :: Python :: 3.7
Classifier: Programming Language :: Python :: 3.8
Classifier: Programming Language :: Python :: 3.9
Classifier: Programming Language :: Python :: Implementation
Classifier: Programming Language :: Python :: Implementation :: PyPy
Classifier: Topic :: Software Development :: Libraries :: Application Frameworks
Requires-Python: >=3.5
License-File: LICENSE.md
